{
  "iterations": [
    {
      "iteration": 2,
      "timestamp": "2026-02-25T08:26:38Z",
      "note": "Completed dev build baseline verification (lint/build success). Fixed TSX files."
    },
    {
      "iteration": 3,
      "timestamp": "2026-02-25T09:00:56Z",
      "note": "Completed E6-S2 (Predictive queue risk cards) and E6-S4 (Decision trace panel). Components and tests written and passed."
    },
    {
      "iteration": 4,
      "timestamp": "2026-02-25T09:03:46Z",
      "note": "Completed E6-S3 (Prompt variable diff + approval workflow). Tests written and passing."
    },
    {
      "iteration": 5,
      "timestamp": "2026-02-26T10:40:15Z",
      "note": "Completed E6-S5 (Alert center remediation copy). Components and tests written and passing."
    },
    {
      "iteration": 6,
      "timestamp": "2026-02-26T10:46:56Z",
      "note": "Completed E6-S6 (Timeline conflict detection hints). Components and tests written and passing."
    },
    {
      "iteration": 7,
      "timestamp": "2026-02-26T10:51:49Z",
      "note": "Completed E7-S1 (Global keyboard map). Components and tests written and passing."
    },
    {
      "iteration": 8,
      "timestamp": "2026-02-27T05:54:23Z",
      "note": "Completed E7-S2 (Reduced-motion alternatives). Component and tests written and passing."
    }
  ]
}